{
 "marks": {
  "fermatLastTheoremThree": "✅✅",
  "fermatLastTheoremFour": "✅✅",
  "FermatLastTheorem.of_odd_primes": "✅✅",
  "fermat_last_theorem": "❌",
  "fermatLastTheoremFor_of_five_le": "❌",
  "FreyPackage": "✅✅",
  "FreyPackage.freyCurve": "✅✅",
  "FreyPackage.mazur": "❌",
  "FreyPackage.exists_torsion_embedding_of_not_isIrreducible": "❌",
  "FreyPackage.exists_two_torsion_and_p_point_of_not_isIrreducible": "❌",
  "FreyPackage.exists_p_point_of_not_isIrreducible": "❌",
  "minkowski_character_trivial": "❌",
  "open_normal_subgroup_eq_top_of_inertia_le": "❌",
  "isUnramifiedAt_of_inertia_le_fixingSubgroup": "❌",
  "inertia_eq_bot_of_le_fixingSubgroup": "❌",
  "FreyPackage.exists_p_point_of_not_isIrreducible_of_minkowski": "❌",
  "FreyPackage.stable_line_dichotomy_of_not_isIrreducible": "❌",
  "FreyPackage.subquotient_character_unramified": "❌",
  "FreyPackage.inertia_two_unipotent": "❌",
  "WeierstrassCurve.torsion_unipotent_of_multiplicative_reduction": "❌",
  "FreyPackage.subquotient_character_unramified_at_p": "❌",
  "FreyPackage.exists_quotient_curve_point": "❌",
  "WeierstrassCurve.exists_point_eq_baseChange_of_fixed": "❌",
  "GaloisRepresentation.exists_stable_line_of_not_isIrreducible": "✅✅",
  "FreyPackage.freyCurve_two_torsion_embedding": "❌",
  "embedding_assembly": "❌",
  "WeierstrassCurve.mazur_torsion_bound": "❌",
  "WeierstrassCurve.mazur_classification": "❌",
  "FreyPackage.galoisRep_not_irreducible": "❌",
  "FreyCurve.torsion_isHardlyRamified": "❌",
  "FreyCurve.torsion_det": "❌",
  "WeilPairing.exists_weilPairing": "❌",
  "WeilPairing.det_galoisRep_eq_cyclotomic": "❌",
  "WeilPairing.exists_frobenius_reduction_model": "❌",
  "WeilPairing.exists_weilPairing_frobenius": "❌",
  "WeilPairing.det_frobeniusTorsionEnd": "❌",
  "WeilPairing.det_galoisRep_globalFrob": "❌",
  "WeilPairing.pairing_map_eq_det_smul": "❌",
  "FreyCurve.torsion_isUnramified": "❌",
  "FreyCurve.torsion_isUnramified_of_good": "❌",
  "FreyPackage.freyCurve_hasGoodReduction_of_not_dvd": "❌",
  "WeierstrassCurve.isUnramifiedAt_of_hasGoodReduction": "❌",
  "WeierstrassCurve.torsion_unramified_of_good_reduction": "✅✅",
  "FreyCurve.torsion_isUnramified_of_multiplicative": "❌",
  "FreyPackage.freyCurve_hasMultiplicativeReduction_of_dvd": "❌",
  "WeierstrassCurve.isUnramifiedAt_of_hasMultiplicativeReduction": "❌",
  "FreyCurve.torsion_isFlat": "❌",
  "FreyCurve.torsion_isFlat_of_good": "❌",
  "WeierstrassCurve.isFlatAt_of_hasGoodReduction": "❌",
  "WeierstrassCurve.torsion_flat_of_good_reduction": "❌",
  "FreyCurve.torsion_isFlat_of_multiplicative": "❌",
  "WeierstrassCurve.isFlatAt_of_hasMultiplicativeReduction": "❌",
  "WeierstrassCurve.torsion_flat_of_multiplicative_reduction": "❌",
  "GaloisRep.isFlatAt_of_dvr_package": "✅✅",
  "GaloisRep.hasFlatProlongationAt_of_dvr_package": "✅✅",
  "GaloisRep.hasFlatProlongationAt_of_hopf_package": "✅✅",
  "algHomEquivOfFinite": "✅✅",
  "FreyCurve.torsion_isTameAtTwo": "❌",
  "FreyPackage.freyCurve_hasMultiplicativeReduction_at_two": "❌",
  "WeierstrassCurve.isTameAtTwo_of_hasMultiplicativeReduction": "❌",
  "GaloisRepresentation.not_isIrreducible_of_isHardlyRamified": "❌",
  "GaloisRepresentation.exists_hardlyRamifiedLift": "❌",
  "GaloisRepresentation.residual_charFrob_eq": "❌",
  "GaloisRepresentation.IsHardlyRamified.mem_isCompatible": "❌",
  "GaloisRepresentation.residual_charFrob_eq_of_family": "❌",
  "GaloisRepresentation.IsHardlyRamified.exists_line_with_locally_unramified_quotCharacter": "❌",
  "GaloisRepresentation.IsHardlyRamified.mod_three_reducible": "❌",
  "GaloisRepresentation.IsHardlyRamified.mod_three": "❌",
  "valued_natCast_adicCompletionIntegers_eq_one": "✅✅",
  "adicArithFrob_rootsOfUnity_pow": "✅✅",
  "cyclotomicCharacter_adicArithFrob": "✅✅",
  "GaloisRepresentation.IsHardlyRamified.exists_global_triangular_of_residual_trivial_quotient": "❌",
  "GaloisRepresentation.IsHardlyRamified.exists_frobenius_triangular_of_residual_trivial_quotient": "❌",
  "GaloisRepresentation.IsHardlyRamified.isTameAtTwo_baseChange_residue": "❌",
  "GaloisRepresentation.IsHardlyRamified.flat_space_equiv_residue": "❌",
  "GaloisRepresentation.IsHardlyRamified.hasFlatProlongationAt_of_subsingleton": "❌",
  "GaloisRepresentation.IsHardlyRamified.isFlatAt_baseChange_residue": "❌",
  "GaloisRepresentation.IsHardlyRamified.exists_residue_package": "❌",
  "GaloisRepresentation.IsHardlyRamified.exists_residual_isHardlyRamified": "❌",
  "GaloisRepresentation.IsHardlyRamified.exists_frobenius_triangular": "❌",
  "GaloisRepresentation.IsHardlyRamified.three_adic": "❌",
  "GaloisRepresentation.not_isIrreducible_of_charFrob_eq": "❌",
  "GaloisRepresentation.dense_conjClasses_globalFrob": "✅",
  "GaloisRepresentation.exists_frobenius_conj_mem_coset": "❌",
  "GaloisRepresentation.not_isIrreducible_of_charpoly_eq": "✅✅",
  "BrauerNesbitt.exists_fixed_of_unipotent": "✅✅",
  "BrauerNesbitt.exists_common_eigenvector_of_commuting": "✅✅",
  "GaloisRepresentation.cyclotomicCharacterModL_globalFrob": "✅✅",
  "GaloisRepresentation.cyclotomicCharacter_globalFrob": "✅✅",
  "GaloisRepresentation.toZMod_eq_ringEquivCongr_comp_toZModPow": "✅✅",
  "WeierstrassCurve.n_torsion_finite": "✅✅",
  "WeierstrassCurve.n_torsion_card": "✅✅",
  "TorsionCard.smul_surjective": "✅✅",
  "TorsionCard.smul_some_eq_zero_iff": "✅✅",
  "TorsionCard.exists_smul_some_eq": "✅✅",
  "TorsionCard.zsmul_some_aux": "✅✅",
  "TorsionCard.evalEval_ψ_quadratic": "✅✅",
  "TorsionCard.psi_tracking_prev_zero": "✅✅",
  "TorsionCard.psi_tracking_prev2_zero": "✅✅",
  "TorsionCard.psi_eq_zero_iff_dvd": "✅✅",
  "PsiSumCompanion.evalEval_ψ_sum": "✅✅",
  "EllipticDivisibilitySequence.normEDS_sum_companion": "✅✅",
  "TorsionCard.exists_point_x_smul": "✅✅",
  "TorsionCard.prime_torsion_card": "✅✅",
  "TorsionCard.separable_preΨ'": "✅✅",
  "TorsionCard.isCoprime_Ψ₂Sq_preΨ'": "✅✅",
  "TorsionCard.separable_Ψ₂Sq": "✅✅",
  "WeierstrassCurve.galoisRep": "✅✅",
  "group_theory_lemma": "✅✅",
  "torsion_unipotent_of_split_multiplicative_adic": "❌",
  "WeierstrassCurve.exists_tateEquivSepClosure": "❌",
  "WeierstrassCurve.exists_variableChange_tateCurve": "✅✅",
  "WeierstrassCurve.tate_inertia_unipotent": "❌",
  "WeierstrassCurve.torsion_unipotent_of_nonsplit_multiplicative_adic": "❌",
  "ValuationSubring.inertia_fixes_of_pow_eq": "✅✅",
  "WeierstrassCurve.tate_inertia_trivial": "❌",
  "valuation_eq_one_of_padicValRat_eq_zero": "❌",
  "exists_unit_qUnit_mul_inv_pow_isUnit": "❌",
  "torsion_trivial_of_split_multiplicative_adic": "❌",
  "WeierstrassCurve.torsion_trivial_of_nonsplit_multiplicative_adic": "❌",
  "WeierstrassCurve.torsion_trivial_of_multiplicative_reduction": "❌",
  "WeierstrassCurve.tate_inertia_unipotent_of_nonsplit": "❌",
  "WeierstrassCurve.tate_inertia_trivial_of_nonsplit": "❌",
  "inertia_fixes_algHom_of_unramified_gen": "❌",
  "ValuationSubring.inertia_fixes_root_of_separable_residue": "✅✅",
  "WeierstrassCurve.exists_tateCurveEquivSepClosure": "❌",
  "WeierstrassCurve.exists_tateCurveHomSepClosure": "❌",
  "TateCurve.exists_annulus_bilateralX_eq": "❌",
  "TateCurve.pointMapQuot_surjective": "❌",
  "TateCurve.bilateral_chordY_cleared": "❌",
  "TateCurve.bilateral_chordX_cleared": "❌",
  "TateCurve.bilateral_add_of_X_ne": "❌",
  "TateCurve.pointMapQuot_add": "❌",
  "TateCurve.tateCurveEquiv": "❌",
  "WeierstrassCurve.tateGluePointAt": "❌",
  "WeierstrassCurve.tateGluePointAt_inclusion": "❌",
  "WeierstrassCurve.tateGluePointAt_conj": "❌",
  "WeierstrassCurve.tateGluePointAt_mul": "❌",
  "WeierstrassCurve.tateGluePointAt_eq_zero_iff": "❌",
  "WeierstrassCurve.exists_tateCurveHomSepClosure_of_finiteLevel": "❌",
  "WeierstrassCurve.exists_tateTorsionQuotient": "❌",
  "hasMultiplicativeReduction_padic": "❌",
  "exists_tame_quotient_of_split_padic_two": "❌",
  "WeierstrassCurve.exists_tame_quotient_of_nonsplit_padic_two": "❌",
  "inertia_fixes_algHom_of_unramified_gen_padic_two": "❌",
  "WeierstrassCurve.hasSplitMultiplicativeReduction_tateCurve": "✅✅",
  "WeierstrassCurve.isElliptic_tateCurve_and_j": "✅✅",
  "WeierstrassCurve.exists_variableChange_of_j_eq_of_split": "✅✅",
  "WeierstrassCurve.Δ_tateCurve_eq_evalInt": "✅✅",
  "TateCurve.evalInt_subst": "✅✅",
  "TateCurve.ΔFormal_eq": "✅✅",
  "WeierstrassCurve.hasSplitMultiplicativeReduction_minimal_smul": "✅✅",
  "WeierstrassCurve.isSquare_of_scaled_split": "✅✅",
  "WeierstrassCurve.isSquare_neg_c₄_mul_c₆_of_split": "✅✅",
  "GaloisRepresentation.natCard_residue_quotient_toHeightOneSpectrum": "✅✅",
  "GaloisRepresentation.IsHardlyRamified.exists_conj_cyclotomicCharacter_three": "❌",
  "GaloisRepresentation.IsHardlyRamified.finrank_eigenspace_one_of_involution": "❌",
  "GaloisRepresentation.IsHardlyRamified.not_isAbsolutelyIrreducible": "❌",
  "GaloisRepresentation.IsHardlyRamified.serre_elimination": "❌",
  "GaloisRepresentation.IsHardlyRamified.serre_elimination_noncyclic": "❌",
  "GaloisRepresentation.IsHardlyRamified.serre_elimination_semidirect": "❌",
  "GaloisRepresentation.IsHardlyRamified.serre_elimination_arith": "❌",
  "GaloisRepresentation.IsHardlyRamified.exists_line_with_unramified_quotCharacter_at_three": "❌",
  "GaloisRepresentation.IsHardlyRamified.quotCharacter_unramified_at_two": "❌",
  "GaloisRepresentation.IsHardlyRamified.quotCharacter_inertia_two_ker": "❌",
  "GaloisRepresentation.IsHardlyRamified.cyclotomicCharacter_algebraMap_eq_one_of_inertia_two": "❌",
  "GaloisRepresentation.IsHardlyRamified.localInertia_two_eq_map_padic": "❌",
  "Dickson.classification_tame": "✅✅",
  "Dickson.classification_wild": "✅✅",
  "OddRep.isIrreducible_iff_isAbsolutelyIrreducible": "✅✅",
  "TateCurve.bilateral_chordX_cleared_window": "❌",
  "TateCurve.bilateral_chordX_cleared_shifted": "❌",
  "TateCurve.bilateral_chordY_cleared_window": "❌",
  "TateCurve.bilateral_chordY_cleared_shifted": "❌",
  "TateCurve.evalA_chordX": "❌",
  "TateCurve.evalA_chordY": "❌",
  "TateCurve.chordX_formal": "❌",
  "TateCurve.chordY_formal": "❌",
  "TateCurve.evalA_chordX_of_formal": "❌",
  "TateCurve.evalA_chordY_of_formal": "❌",
  "TateCurve.chordX_ratFunc₂": "❌",
  "TateCurve.chordY_ratFunc₂": "❌",
  "TateCurve.summable_evalA_XA_ext": "❌",
  "TateCurve.summable_evalA_YA_ext": "❌",
  "TateCurve.evalA_XA_eq_bilateralX_ext": "❌",
  "TateCurve.evalA_YA_eq_bilateralY_ext": "❌",
  "TateCurve.pointMap_mul": "❌",
  "TateCurve.exists_annulus_bilateralX_eq_of_one_le": "❌",
  "TateCurve.exists_annulus_bilateralX_eq_of_lt_one": "❌",
  "TateCurve.coeffRingEval_map": "❌",
  "TateCurve.valuation_hasSum_sub_sum_le": "❌",
  "TateCurve.evalA_XA_map": "❌",
  "TateCurve.evalA_YA_map": "❌",
  "TateCurve.bilateralX_map": "❌",
  "TateCurve.bilateralY_map": "❌",
  "TateCurve.tateCurve_map": "❌",
  "exists_valuativeRel_sepClosure": "❌",
  "isNonarchimedeanLocalField_intermediate": "❌",
  "locallyCompactSpace_intermediate": "❌",
  "WeilPairing.exists_weilPairing_mu": "❌"
 },
 "children": {
  "fermatLastTheoremThree": [],
  "fermatLastTheoremFour": [],
  "FermatLastTheorem.of_odd_primes": [
   "fermatLastTheoremFour"
  ],
  "fermat_last_theorem": [],
  "fermatLastTheoremFor_of_five_le": [],
  "FreyPackage": [],
  "FreyPackage.freyCurve": [
   "FreyPackage"
  ],
  "FreyPackage.mazur": [],
  "FreyPackage.exists_torsion_embedding_of_not_isIrreducible": [],
  "FreyPackage.exists_two_torsion_and_p_point_of_not_isIrreducible": [],
  "FreyPackage.exists_p_point_of_not_isIrreducible": [],
  "minkowski_character_trivial": [],
  "open_normal_subgroup_eq_top_of_inertia_le": [],
  "isUnramifiedAt_of_inertia_le_fixingSubgroup": [],
  "inertia_eq_bot_of_le_fixingSubgroup": [],
  "FreyPackage.exists_p_point_of_not_isIrreducible_of_minkowski": [],
  "FreyPackage.stable_line_dichotomy_of_not_isIrreducible": [],
  "FreyPackage.subquotient_character_unramified": [],
  "FreyPackage.inertia_two_unipotent": [],
  "WeierstrassCurve.torsion_unipotent_of_multiplicative_reduction": [],
  "FreyPackage.subquotient_character_unramified_at_p": [],
  "FreyPackage.exists_quotient_curve_point": [],
  "WeierstrassCurve.exists_point_eq_baseChange_of_fixed": [],
  "GaloisRepresentation.exists_stable_line_of_not_isIrreducible": [],
  "FreyPackage.freyCurve_two_torsion_embedding": [],
  "embedding_assembly": [],
  "WeierstrassCurve.mazur_torsion_bound": [],
  "WeierstrassCurve.mazur_classification": [],
  "FreyPackage.galoisRep_not_irreducible": [],
  "FreyCurve.torsion_isHardlyRamified": [],
  "FreyCurve.torsion_det": [],
  "WeilPairing.exists_weilPairing": [],
  "WeilPairing.det_galoisRep_eq_cyclotomic": [],
  "WeilPairing.exists_frobenius_reduction_model": [],
  "WeilPairing.exists_weilPairing_frobenius": [],
  "WeilPairing.det_frobeniusTorsionEnd": [],
  "WeilPairing.det_galoisRep_globalFrob": [],
  "WeilPairing.pairing_map_eq_det_smul": [],
  "FreyCurve.torsion_isUnramified": [],
  "FreyCurve.torsion_isUnramified_of_good": [],
  "FreyPackage.freyCurve_hasGoodReduction_of_not_dvd": [],
  "WeierstrassCurve.isUnramifiedAt_of_hasGoodReduction": [],
  "WeierstrassCurve.torsion_unramified_of_good_reduction": [
   "TorsionCard.smul_some_eq_zero_iff",
   "TorsionCard.isCoprime_Ψ₂Sq_preΨ'",
   "TorsionCard.separable_preΨ'"
  ],
  "FreyCurve.torsion_isUnramified_of_multiplicative": [],
  "FreyPackage.freyCurve_hasMultiplicativeReduction_of_dvd": [],
  "WeierstrassCurve.isUnramifiedAt_of_hasMultiplicativeReduction": [],
  "FreyCurve.torsion_isFlat": [],
  "FreyCurve.torsion_isFlat_of_good": [],
  "WeierstrassCurve.isFlatAt_of_hasGoodReduction": [],
  "WeierstrassCurve.torsion_flat_of_good_reduction": [],
  "FreyCurve.torsion_isFlat_of_multiplicative": [],
  "WeierstrassCurve.isFlatAt_of_hasMultiplicativeReduction": [],
  "WeierstrassCurve.torsion_flat_of_multiplicative_reduction": [],
  "GaloisRep.isFlatAt_of_dvr_package": [
   "GaloisRep.hasFlatProlongationAt_of_dvr_package"
  ],
  "GaloisRep.hasFlatProlongationAt_of_dvr_package": [
   "GaloisRep.hasFlatProlongationAt_of_hopf_package"
  ],
  "GaloisRep.hasFlatProlongationAt_of_hopf_package": [
   "algHomEquivOfFinite"
  ],
  "algHomEquivOfFinite": [],
  "FreyCurve.torsion_isTameAtTwo": [],
  "FreyPackage.freyCurve_hasMultiplicativeReduction_at_two": [],
  "WeierstrassCurve.isTameAtTwo_of_hasMultiplicativeReduction": [],
  "GaloisRepresentation.not_isIrreducible_of_isHardlyRamified": [],
  "GaloisRepresentation.exists_hardlyRamifiedLift": [],
  "GaloisRepresentation.residual_charFrob_eq": [],
  "GaloisRepresentation.IsHardlyRamified.mem_isCompatible": [],
  "GaloisRepresentation.residual_charFrob_eq_of_family": [],
  "GaloisRepresentation.IsHardlyRamified.exists_line_with_locally_unramified_quotCharacter": [],
  "GaloisRepresentation.IsHardlyRamified.mod_three_reducible": [],
  "GaloisRepresentation.IsHardlyRamified.mod_three": [],
  "valued_natCast_adicCompletionIntegers_eq_one": [],
  "adicArithFrob_rootsOfUnity_pow": [
   "GaloisRepresentation.natCard_residue_quotient_toHeightOneSpectrum",
   "valued_natCast_adicCompletionIntegers_eq_one"
  ],
  "cyclotomicCharacter_adicArithFrob": [
   "adicArithFrob_rootsOfUnity_pow"
  ],
  "GaloisRepresentation.IsHardlyRamified.exists_global_triangular_of_residual_trivial_quotient": [],
  "GaloisRepresentation.IsHardlyRamified.exists_frobenius_triangular_of_residual_trivial_quotient": [],
  "GaloisRepresentation.IsHardlyRamified.isTameAtTwo_baseChange_residue": [],
  "GaloisRepresentation.IsHardlyRamified.flat_space_equiv_residue": [],
  "GaloisRepresentation.IsHardlyRamified.hasFlatProlongationAt_of_subsingleton": [],
  "GaloisRepresentation.IsHardlyRamified.isFlatAt_baseChange_residue": [],
  "GaloisRepresentation.IsHardlyRamified.exists_residue_package": [],
  "GaloisRepresentation.IsHardlyRamified.exists_residual_isHardlyRamified": [],
  "GaloisRepresentation.IsHardlyRamified.exists_frobenius_triangular": [],
  "GaloisRepresentation.IsHardlyRamified.three_adic": [],
  "GaloisRepresentation.not_isIrreducible_of_charFrob_eq": [],
  "GaloisRepresentation.dense_conjClasses_globalFrob": [
   "GaloisRepresentation.exists_frobenius_conj_mem_coset"
  ],
  "GaloisRepresentation.exists_frobenius_conj_mem_coset": [],
  "GaloisRepresentation.not_isIrreducible_of_charpoly_eq": [
   "BrauerNesbitt.exists_common_eigenvector_of_commuting",
   "BrauerNesbitt.exists_fixed_of_unipotent"
  ],
  "BrauerNesbitt.exists_fixed_of_unipotent": [],
  "BrauerNesbitt.exists_common_eigenvector_of_commuting": [],
  "GaloisRepresentation.cyclotomicCharacterModL_globalFrob": [
   "GaloisRepresentation.cyclotomicCharacter_globalFrob"
  ],
  "GaloisRepresentation.cyclotomicCharacter_globalFrob": [
   "GaloisRepresentation.natCard_residue_quotient_toHeightOneSpectrum"
  ],
  "GaloisRepresentation.toZMod_eq_ringEquivCongr_comp_toZModPow": [],
  "WeierstrassCurve.n_torsion_finite": [
   "TorsionCard.prime_torsion_card",
   "TorsionCard.smul_surjective"
  ],
  "WeierstrassCurve.n_torsion_card": [
   "TorsionCard.prime_torsion_card",
   "TorsionCard.smul_surjective"
  ],
  "TorsionCard.smul_surjective": [
   "TorsionCard.exists_point_x_smul",
   "TorsionCard.exists_smul_some_eq"
  ],
  "TorsionCard.smul_some_eq_zero_iff": [
   "TorsionCard.zsmul_some_aux"
  ],
  "TorsionCard.exists_smul_some_eq": [
   "TorsionCard.zsmul_some_aux"
  ],
  "TorsionCard.zsmul_some_aux": [
   "PsiSumCompanion.evalEval_ψ_sum",
   "TorsionCard.psi_tracking_prev2_zero",
   "TorsionCard.psi_tracking_prev_zero",
   "TorsionCard.psi_eq_zero_iff_dvd",
   "TorsionCard.evalEval_ψ_quadratic"
  ],
  "TorsionCard.evalEval_ψ_quadratic": [],
  "TorsionCard.psi_tracking_prev_zero": [
   "TorsionCard.psi_eq_zero_iff_dvd",
   "EllipticDivisibilitySequence.normEDS_sum_companion"
  ],
  "TorsionCard.psi_tracking_prev2_zero": [
   "EllipticDivisibilitySequence.normEDS_sum_companion",
   "TorsionCard.psi_eq_zero_iff_dvd"
  ],
  "TorsionCard.psi_eq_zero_iff_dvd": [],
  "PsiSumCompanion.evalEval_ψ_sum": [
   "EllipticDivisibilitySequence.normEDS_sum_companion"
  ],
  "EllipticDivisibilitySequence.normEDS_sum_companion": [],
  "TorsionCard.exists_point_x_smul": [],
  "TorsionCard.prime_torsion_card": [
   "TorsionCard.isCoprime_Ψ₂Sq_preΨ'",
   "TorsionCard.separable_preΨ'",
   "TorsionCard.smul_some_eq_zero_iff",
   "TorsionCard.separable_Ψ₂Sq"
  ],
  "TorsionCard.separable_preΨ'": [
   "TorsionCard.exists_smul_some_eq",
   "TorsionCard.smul_some_eq_zero_iff",
   "PsiSumCompanion.evalEval_ψ_sum",
   "TorsionCard.psi_tracking_prev2_zero",
   "TorsionCard.psi_tracking_prev_zero",
   "TorsionCard.psi_eq_zero_iff_dvd",
   "TorsionCard.evalEval_ψ_quadratic"
  ],
  "TorsionCard.isCoprime_Ψ₂Sq_preΨ'": [
   "TorsionCard.smul_some_eq_zero_iff"
  ],
  "TorsionCard.separable_Ψ₂Sq": [],
  "WeierstrassCurve.galoisRep": [
   "WeierstrassCurve.n_torsion_finite"
  ],
  "group_theory_lemma": [],
  "torsion_unipotent_of_split_multiplicative_adic": [],
  "WeierstrassCurve.exists_tateEquivSepClosure": [],
  "WeierstrassCurve.exists_variableChange_tateCurve": [
   "WeierstrassCurve.exists_variableChange_of_j_eq_of_split",
   "WeierstrassCurve.hasSplitMultiplicativeReduction_tateCurve",
   "WeierstrassCurve.isElliptic_tateCurve_and_j"
  ],
  "WeierstrassCurve.tate_inertia_unipotent": [],
  "WeierstrassCurve.torsion_unipotent_of_nonsplit_multiplicative_adic": [],
  "ValuationSubring.inertia_fixes_of_pow_eq": [],
  "WeierstrassCurve.tate_inertia_trivial": [],
  "valuation_eq_one_of_padicValRat_eq_zero": [],
  "exists_unit_qUnit_mul_inv_pow_isUnit": [],
  "torsion_trivial_of_split_multiplicative_adic": [],
  "WeierstrassCurve.torsion_trivial_of_nonsplit_multiplicative_adic": [],
  "WeierstrassCurve.torsion_trivial_of_multiplicative_reduction": [],
  "WeierstrassCurve.tate_inertia_unipotent_of_nonsplit": [],
  "WeierstrassCurve.tate_inertia_trivial_of_nonsplit": [],
  "inertia_fixes_algHom_of_unramified_gen": [],
  "ValuationSubring.inertia_fixes_root_of_separable_residue": [],
  "WeierstrassCurve.exists_tateCurveEquivSepClosure": [],
  "WeierstrassCurve.exists_tateCurveHomSepClosure": [],
  "TateCurve.exists_annulus_bilateralX_eq": [],
  "TateCurve.pointMapQuot_surjective": [],
  "TateCurve.bilateral_chordY_cleared": [],
  "TateCurve.bilateral_chordX_cleared": [],
  "TateCurve.bilateral_add_of_X_ne": [],
  "TateCurve.pointMapQuot_add": [],
  "TateCurve.tateCurveEquiv": [],
  "WeierstrassCurve.tateGluePointAt": [],
  "WeierstrassCurve.tateGluePointAt_inclusion": [],
  "WeierstrassCurve.tateGluePointAt_conj": [],
  "WeierstrassCurve.tateGluePointAt_mul": [],
  "WeierstrassCurve.tateGluePointAt_eq_zero_iff": [],
  "WeierstrassCurve.exists_tateCurveHomSepClosure_of_finiteLevel": [],
  "WeierstrassCurve.exists_tateTorsionQuotient": [],
  "hasMultiplicativeReduction_padic": [],
  "exists_tame_quotient_of_split_padic_two": [],
  "WeierstrassCurve.exists_tame_quotient_of_nonsplit_padic_two": [],
  "inertia_fixes_algHom_of_unramified_gen_padic_two": [],
  "WeierstrassCurve.hasSplitMultiplicativeReduction_tateCurve": [],
  "WeierstrassCurve.isElliptic_tateCurve_and_j": [
   "WeierstrassCurve.Δ_tateCurve_eq_evalInt",
   "TateCurve.evalInt_subst"
  ],
  "WeierstrassCurve.exists_variableChange_of_j_eq_of_split": [
   "WeierstrassCurve.hasSplitMultiplicativeReduction_minimal_smul",
   "WeierstrassCurve.isSquare_of_scaled_split"
  ],
  "WeierstrassCurve.Δ_tateCurve_eq_evalInt": [
   "TateCurve.ΔFormal_eq"
  ],
  "TateCurve.evalInt_subst": [],
  "TateCurve.ΔFormal_eq": [],
  "WeierstrassCurve.hasSplitMultiplicativeReduction_minimal_smul": [],
  "WeierstrassCurve.isSquare_of_scaled_split": [
   "WeierstrassCurve.isSquare_neg_c₄_mul_c₆_of_split"
  ],
  "WeierstrassCurve.isSquare_neg_c₄_mul_c₆_of_split": [],
  "GaloisRepresentation.natCard_residue_quotient_toHeightOneSpectrum": [],
  "GaloisRepresentation.IsHardlyRamified.exists_conj_cyclotomicCharacter_three": [],
  "GaloisRepresentation.IsHardlyRamified.finrank_eigenspace_one_of_involution": [],
  "GaloisRepresentation.IsHardlyRamified.not_isAbsolutelyIrreducible": [],
  "GaloisRepresentation.IsHardlyRamified.serre_elimination": [],
  "GaloisRepresentation.IsHardlyRamified.serre_elimination_noncyclic": [],
  "GaloisRepresentation.IsHardlyRamified.serre_elimination_semidirect": [],
  "GaloisRepresentation.IsHardlyRamified.serre_elimination_arith": [],
  "GaloisRepresentation.IsHardlyRamified.exists_line_with_unramified_quotCharacter_at_three": [],
  "GaloisRepresentation.IsHardlyRamified.quotCharacter_unramified_at_two": [],
  "GaloisRepresentation.IsHardlyRamified.quotCharacter_inertia_two_ker": [],
  "GaloisRepresentation.IsHardlyRamified.cyclotomicCharacter_algebraMap_eq_one_of_inertia_two": [],
  "GaloisRepresentation.IsHardlyRamified.localInertia_two_eq_map_padic": [],
  "Dickson.classification_tame": [],
  "Dickson.classification_wild": [],
  "OddRep.isIrreducible_iff_isAbsolutelyIrreducible": [],
  "TateCurve.bilateral_chordX_cleared_window": [],
  "TateCurve.bilateral_chordX_cleared_shifted": [],
  "TateCurve.bilateral_chordY_cleared_window": [],
  "TateCurve.bilateral_chordY_cleared_shifted": [],
  "TateCurve.evalA_chordX": [],
  "TateCurve.evalA_chordY": [],
  "TateCurve.chordX_formal": [],
  "TateCurve.chordY_formal": [],
  "TateCurve.evalA_chordX_of_formal": [],
  "TateCurve.evalA_chordY_of_formal": [],
  "TateCurve.chordX_ratFunc₂": [],
  "TateCurve.chordY_ratFunc₂": [],
  "TateCurve.summable_evalA_XA_ext": [],
  "TateCurve.summable_evalA_YA_ext": [],
  "TateCurve.evalA_XA_eq_bilateralX_ext": [],
  "TateCurve.evalA_YA_eq_bilateralY_ext": [],
  "TateCurve.pointMap_mul": [],
  "TateCurve.exists_annulus_bilateralX_eq_of_one_le": [],
  "TateCurve.exists_annulus_bilateralX_eq_of_lt_one": [],
  "TateCurve.coeffRingEval_map": [],
  "TateCurve.valuation_hasSum_sub_sum_le": [],
  "TateCurve.evalA_XA_map": [],
  "TateCurve.evalA_YA_map": [],
  "TateCurve.bilateralX_map": [],
  "TateCurve.bilateralY_map": [],
  "TateCurve.tateCurve_map": [],
  "exists_valuativeRel_sepClosure": [],
  "isNonarchimedeanLocalField_intermediate": [],
  "locallyCompactSpace_intermediate": [],
  "WeilPairing.exists_weilPairing_mu": []
 },
 "roots": [
  "fermatLastTheoremThree",
  "FermatLastTheorem.of_odd_primes",
  "fermat_last_theorem",
  "fermatLastTheoremFor_of_five_le",
  "FreyPackage.freyCurve",
  "FreyPackage.mazur",
  "FreyPackage.exists_torsion_embedding_of_not_isIrreducible",
  "FreyPackage.exists_two_torsion_and_p_point_of_not_isIrreducible",
  "FreyPackage.exists_p_point_of_not_isIrreducible",
  "minkowski_character_trivial",
  "open_normal_subgroup_eq_top_of_inertia_le",
  "isUnramifiedAt_of_inertia_le_fixingSubgroup",
  "inertia_eq_bot_of_le_fixingSubgroup",
  "FreyPackage.exists_p_point_of_not_isIrreducible_of_minkowski",
  "FreyPackage.stable_line_dichotomy_of_not_isIrreducible",
  "FreyPackage.subquotient_character_unramified",
  "FreyPackage.inertia_two_unipotent",
  "WeierstrassCurve.torsion_unipotent_of_multiplicative_reduction",
  "FreyPackage.subquotient_character_unramified_at_p",
  "FreyPackage.exists_quotient_curve_point",
  "WeierstrassCurve.exists_point_eq_baseChange_of_fixed",
  "GaloisRepresentation.exists_stable_line_of_not_isIrreducible",
  "FreyPackage.freyCurve_two_torsion_embedding",
  "embedding_assembly",
  "WeierstrassCurve.mazur_torsion_bound",
  "WeierstrassCurve.mazur_classification",
  "FreyPackage.galoisRep_not_irreducible",
  "FreyCurve.torsion_isHardlyRamified",
  "FreyCurve.torsion_det",
  "WeilPairing.exists_weilPairing",
  "WeilPairing.det_galoisRep_eq_cyclotomic",
  "WeilPairing.exists_frobenius_reduction_model",
  "WeilPairing.exists_weilPairing_frobenius",
  "WeilPairing.det_frobeniusTorsionEnd",
  "WeilPairing.det_galoisRep_globalFrob",
  "WeilPairing.pairing_map_eq_det_smul",
  "FreyCurve.torsion_isUnramified",
  "FreyCurve.torsion_isUnramified_of_good",
  "FreyPackage.freyCurve_hasGoodReduction_of_not_dvd",
  "WeierstrassCurve.isUnramifiedAt_of_hasGoodReduction",
  "WeierstrassCurve.torsion_unramified_of_good_reduction",
  "FreyCurve.torsion_isUnramified_of_multiplicative",
  "FreyPackage.freyCurve_hasMultiplicativeReduction_of_dvd",
  "WeierstrassCurve.isUnramifiedAt_of_hasMultiplicativeReduction",
  "FreyCurve.torsion_isFlat",
  "FreyCurve.torsion_isFlat_of_good",
  "WeierstrassCurve.isFlatAt_of_hasGoodReduction",
  "WeierstrassCurve.torsion_flat_of_good_reduction",
  "FreyCurve.torsion_isFlat_of_multiplicative",
  "WeierstrassCurve.isFlatAt_of_hasMultiplicativeReduction",
  "WeierstrassCurve.torsion_flat_of_multiplicative_reduction",
  "GaloisRep.isFlatAt_of_dvr_package",
  "FreyCurve.torsion_isTameAtTwo",
  "FreyPackage.freyCurve_hasMultiplicativeReduction_at_two",
  "WeierstrassCurve.isTameAtTwo_of_hasMultiplicativeReduction",
  "GaloisRepresentation.not_isIrreducible_of_isHardlyRamified",
  "GaloisRepresentation.exists_hardlyRamifiedLift",
  "GaloisRepresentation.residual_charFrob_eq",
  "GaloisRepresentation.IsHardlyRamified.mem_isCompatible",
  "GaloisRepresentation.residual_charFrob_eq_of_family",
  "GaloisRepresentation.IsHardlyRamified.exists_line_with_locally_unramified_quotCharacter",
  "GaloisRepresentation.IsHardlyRamified.mod_three_reducible",
  "GaloisRepresentation.IsHardlyRamified.mod_three",
  "cyclotomicCharacter_adicArithFrob",
  "GaloisRepresentation.IsHardlyRamified.exists_global_triangular_of_residual_trivial_quotient",
  "GaloisRepresentation.IsHardlyRamified.exists_frobenius_triangular_of_residual_trivial_quotient",
  "GaloisRepresentation.IsHardlyRamified.isTameAtTwo_baseChange_residue",
  "GaloisRepresentation.IsHardlyRamified.flat_space_equiv_residue",
  "GaloisRepresentation.IsHardlyRamified.hasFlatProlongationAt_of_subsingleton",
  "GaloisRepresentation.IsHardlyRamified.isFlatAt_baseChange_residue",
  "GaloisRepresentation.IsHardlyRamified.exists_residue_package",
  "GaloisRepresentation.IsHardlyRamified.exists_residual_isHardlyRamified",
  "GaloisRepresentation.IsHardlyRamified.exists_frobenius_triangular",
  "GaloisRepresentation.IsHardlyRamified.three_adic",
  "GaloisRepresentation.not_isIrreducible_of_charFrob_eq",
  "GaloisRepresentation.dense_conjClasses_globalFrob",
  "GaloisRepresentation.not_isIrreducible_of_charpoly_eq",
  "GaloisRepresentation.cyclotomicCharacterModL_globalFrob",
  "GaloisRepresentation.toZMod_eq_ringEquivCongr_comp_toZModPow",
  "WeierstrassCurve.n_torsion_card",
  "WeierstrassCurve.galoisRep",
  "group_theory_lemma",
  "torsion_unipotent_of_split_multiplicative_adic",
  "WeierstrassCurve.exists_tateEquivSepClosure",
  "WeierstrassCurve.exists_variableChange_tateCurve",
  "WeierstrassCurve.tate_inertia_unipotent",
  "WeierstrassCurve.torsion_unipotent_of_nonsplit_multiplicative_adic",
  "ValuationSubring.inertia_fixes_of_pow_eq",
  "WeierstrassCurve.tate_inertia_trivial",
  "valuation_eq_one_of_padicValRat_eq_zero",
  "exists_unit_qUnit_mul_inv_pow_isUnit",
  "torsion_trivial_of_split_multiplicative_adic",
  "WeierstrassCurve.torsion_trivial_of_nonsplit_multiplicative_adic",
  "WeierstrassCurve.torsion_trivial_of_multiplicative_reduction",
  "WeierstrassCurve.tate_inertia_unipotent_of_nonsplit",
  "WeierstrassCurve.tate_inertia_trivial_of_nonsplit",
  "inertia_fixes_algHom_of_unramified_gen",
  "ValuationSubring.inertia_fixes_root_of_separable_residue",
  "WeierstrassCurve.exists_tateCurveEquivSepClosure",
  "WeierstrassCurve.exists_tateCurveHomSepClosure",
  "TateCurve.exists_annulus_bilateralX_eq",
  "TateCurve.pointMapQuot_surjective",
  "TateCurve.bilateral_chordY_cleared",
  "TateCurve.bilateral_chordX_cleared",
  "TateCurve.bilateral_add_of_X_ne",
  "TateCurve.pointMapQuot_add",
  "TateCurve.tateCurveEquiv",
  "WeierstrassCurve.tateGluePointAt",
  "WeierstrassCurve.tateGluePointAt_inclusion",
  "WeierstrassCurve.tateGluePointAt_conj",
  "WeierstrassCurve.tateGluePointAt_mul",
  "WeierstrassCurve.tateGluePointAt_eq_zero_iff",
  "WeierstrassCurve.exists_tateCurveHomSepClosure_of_finiteLevel",
  "WeierstrassCurve.exists_tateTorsionQuotient",
  "hasMultiplicativeReduction_padic",
  "exists_tame_quotient_of_split_padic_two",
  "WeierstrassCurve.exists_tame_quotient_of_nonsplit_padic_two",
  "inertia_fixes_algHom_of_unramified_gen_padic_two",
  "GaloisRepresentation.IsHardlyRamified.exists_conj_cyclotomicCharacter_three",
  "GaloisRepresentation.IsHardlyRamified.finrank_eigenspace_one_of_involution",
  "GaloisRepresentation.IsHardlyRamified.not_isAbsolutelyIrreducible",
  "GaloisRepresentation.IsHardlyRamified.serre_elimination",
  "GaloisRepresentation.IsHardlyRamified.serre_elimination_noncyclic",
  "GaloisRepresentation.IsHardlyRamified.serre_elimination_semidirect",
  "GaloisRepresentation.IsHardlyRamified.serre_elimination_arith",
  "GaloisRepresentation.IsHardlyRamified.exists_line_with_unramified_quotCharacter_at_three",
  "GaloisRepresentation.IsHardlyRamified.quotCharacter_unramified_at_two",
  "GaloisRepresentation.IsHardlyRamified.quotCharacter_inertia_two_ker",
  "GaloisRepresentation.IsHardlyRamified.cyclotomicCharacter_algebraMap_eq_one_of_inertia_two",
  "GaloisRepresentation.IsHardlyRamified.localInertia_two_eq_map_padic",
  "Dickson.classification_tame",
  "Dickson.classification_wild",
  "OddRep.isIrreducible_iff_isAbsolutelyIrreducible",
  "TateCurve.bilateral_chordX_cleared_window",
  "TateCurve.bilateral_chordX_cleared_shifted",
  "TateCurve.bilateral_chordY_cleared_window",
  "TateCurve.bilateral_chordY_cleared_shifted",
  "TateCurve.evalA_chordX",
  "TateCurve.evalA_chordY",
  "TateCurve.chordX_formal",
  "TateCurve.chordY_formal",
  "TateCurve.evalA_chordX_of_formal",
  "TateCurve.evalA_chordY_of_formal",
  "TateCurve.chordX_ratFunc₂",
  "TateCurve.chordY_ratFunc₂",
  "TateCurve.summable_evalA_XA_ext",
  "TateCurve.summable_evalA_YA_ext",
  "TateCurve.evalA_XA_eq_bilateralX_ext",
  "TateCurve.evalA_YA_eq_bilateralY_ext",
  "TateCurve.pointMap_mul",
  "TateCurve.exists_annulus_bilateralX_eq_of_one_le",
  "TateCurve.exists_annulus_bilateralX_eq_of_lt_one",
  "TateCurve.coeffRingEval_map",
  "TateCurve.valuation_hasSum_sub_sum_le",
  "TateCurve.evalA_XA_map",
  "TateCurve.evalA_YA_map",
  "TateCurve.bilateralX_map",
  "TateCurve.bilateralY_map",
  "TateCurve.tateCurve_map",
  "exists_valuativeRel_sepClosure",
  "isNonarchimedeanLocalField_intermediate",
  "locallyCompactSpace_intermediate",
  "WeilPairing.exists_weilPairing_mu"
 ]
}